odin/__init__.py
odin/example.py
odin/exceptions.py
odin/models/__init__.py
odin/models/certificate_search_response_model.py
odin/models/get_certificate_count.py
odin/models/get_certificate_hash_details.py
odin/models/get_certificates_summary.py
odin/models/get_host_count.py
odin/models/get_hosts_cve_details.py
odin/models/get_hosts_ip_details_response.py
odin/models/get_hosts_summary_response.py
odin/models/search_hosts_response_model.py
odin/odin_client.py
odin_sdk_python_check-0.0.3.dist-info/METADATA
odin_sdk_python_check-0.0.3.dist-info/WHEEL
odin_sdk_python_check-0.0.3.dist-info/RECORD
